flashlight/__init__.py
flashlight/backend/cli.py
flashlight/backend/config.py
flashlight/backend/server.py
flashlight/backend/utility.py
flashlight/client/main.py
flashlight/client/python_tracer.py
flashlight/frontend/dist/3rdpartylicenses.txt
flashlight/frontend/dist/favicon.ico
flashlight/frontend/dist/index.html
flashlight/frontend/dist/inline.318b50c57b4eba3d437b.bundle.js
flashlight/frontend/dist/main.c3b443372c33415d73ad.bundle.js
flashlight/frontend/dist/polyfills.77d59861e39435768676.bundle.js
flashlight/frontend/dist/styles.ac89bfdd6de82636b768.bundle.css
flashlight-0.1.1.dist-info/DESCRIPTION.rst
flashlight-0.1.1.dist-info/LICENSE.txt
flashlight-0.1.1.dist-info/METADATA
flashlight-0.1.1.dist-info/RECORD
flashlight-0.1.1.dist-info/WHEEL
flashlight-0.1.1.dist-info/entry_points.txt
flashlight-0.1.1.dist-info/metadata.json
flashlight-0.1.1.dist-info/top_level.txt
