Metadata-Version: 2.0
Name: flashlight
Version: 0.1.1
Summary: The Visualization Tool For ONNX
Home-page: https://github.com/dlguys/flashlight
Author: Sherin Thomas (hhsecond)
Author-email: sherinct@live.com
License: MIT
Keywords: pytorch visualization onnx
Platform: UNKNOWN
Requires-Dist: sanic (==0.7.0)
